.gitignore
CHANGES.txt
MANIFEST.in
README.txt
bootstrap.py
buildout.cfg
setup.py
collective/__init__.py
collective.btrees.egg-info/PKG-INFO
collective.btrees.egg-info/SOURCES.txt
collective.btrees.egg-info/dependency_links.txt
collective.btrees.egg-info/entry_points.txt
collective.btrees.egg-info/namespace_packages.txt
collective.btrees.egg-info/not-zip-safe
collective.btrees.egg-info/requires.txt
collective.btrees.egg-info/top_level.txt
collective/btrees/__init__.py
collective/btrees/adapters.py
collective/btrees/configure.zcml
collective/btrees/interfaces.py
collective/btrees/testing.py
collective/btrees/tests/__init__.py
collective/btrees/tests/test_functional.py