Metadata-Version: 1.0
Name: collective.btrees
Version: 1.0
Summary: Add btrees in annotations
Home-page: https://github.com/mauritsvanrees/collective.btrees
Author: Maurits van Rees
Author-email: m.van.rees@zestsoftware.nl
License: GPL
Platform: UNKNOWN
Classifier: Framework :: Plone
Classifier: Framework :: Plone :: 3.3
Classifier: Framework :: Plone :: 4.0
Classifier: Framework :: Plone :: 4.1
Classifier: Programming Language :: Python
